AUTHORS
CHANGELOG
CONTRIBUTING.rst
INSTALL
LICENSE
MANIFEST.in
README.rst
VERSION
setup.py
diecutter/__init__.py
diecutter/contextextractors.py
diecutter/exceptions.py
diecutter/github.py
diecutter/local.py
diecutter/service.py
diecutter/settings.py
diecutter/validators.py
diecutter/writers.py
diecutter/wsgi.py
diecutter.egg-info/PKG-INFO
diecutter.egg-info/SOURCES.txt
diecutter.egg-info/dependency_links.txt
diecutter.egg-info/entry_points.txt
diecutter.egg-info/not-zip-safe
diecutter.egg-info/paster_plugins.txt
diecutter.egg-info/requires.txt
diecutter.egg-info/top_level.txt
diecutter/utils/__init__.py
diecutter/utils/dispatchers.py
diecutter/utils/forms.py
diecutter/utils/http.py