Metadata-Version: 1.1
Name: diecutter
Version: 0.7.1
Summary: Templates as a service.
Home-page: https://github.com/diecutter/diecutter
Author: Rémy HUBSCHER
Author-email: hubscher.remy@gmail.com
License: UNKNOWN
Keywords: 'web services' templates template configuration 'code generator'
Platform: UNKNOWN
Classifier: Development Status :: 3 - Alpha
Classifier: Programming Language :: Python :: 2.7
Classifier: Framework :: Pylons
Classifier: Topic :: Internet :: WWW/HTTP
Classifier: Topic :: Internet :: WWW/HTTP :: WSGI :: Application
